dcms/__init__.py
dcms/data.py
dcms/store.py
dcms/_api/__init__.py
dcms/_api/config.py
dcms/_api/data.py
dcms/_api/functions.py
dcms/_api/init.py
dcms/_api/store.py
dcms/_api/database/__init__.py
dcms/_api/database/mongo.py
dcms/_api/database/redis.py
dcms/_api/ext/__init__.py
dcms/_api/ext/executor.py
dcms/_api/ext/web_api.py
dcms/_api/ext/proxy/__init__.py
dcms/_api/ext/proxy/proxy_pool_class.py
dcms/_api/ext/proxy/scrapy_middlewares.py
dcms/_api/ext/web/__init__.py
dcms/database/__init__.py
dcms/ext/__init__.py
dcms/ext/exector.py
dcms/ext/proxy.py
dcms/ext/web_api.py
dcms_sdk-0.0.2.dist-info/LICENSE
dcms_sdk-0.0.2.dist-info/METADATA
dcms_sdk-0.0.2.dist-info/WHEEL
dcms_sdk-0.0.2.dist-info/top_level.txt
dcms_sdk-0.0.2.dist-info/RECORD
