Metadata-Version: 2.1
Name: dcms-sdk
Version: 0.0.2
Summary: the sdk of data crawl manage system
Home-page: https://github.com/qhzhyt/dcms-sdk
Author: easson
Author-email: qhzhyt@163.com
License: UNKNOWN
Platform: UNKNOWN
Classifier: Programming Language :: Python :: 3
Classifier: License :: OSI Approved :: MIT License
Classifier: Operating System :: OS Independent
